discordttp/__init__.py
discordttp/ttp.py
discordttp/src/__init__.py
discordttp/src/ttp.py
discordttp-0.3.2.dist-info/METADATA
discordttp-0.3.2.dist-info/WHEEL
discordttp-0.3.2.dist-info/top_level.txt
discordttp-0.3.2.dist-info/RECORD
